help.txt
helps.py
mesconduit.py
supports.py
conduit/help.txt
conduit/mesconduit.py
mesconduit.egg-info/PKG-INFO
mesconduit.egg-info/SOURCES.txt
mesconduit.egg-info/dependency_links.txt
mesconduit.egg-info/requires.txt
mesconduit.egg-info/top_level.txt
mesconduit-1.1.2.dist-info/LICENSE
mesconduit-1.1.2.dist-info/METADATA
mesconduit-1.1.2.dist-info/WHEEL
mesconduit-1.1.2.dist-info/top_level.txt
mesconduit-1.1.2.dist-info/RECORD
