Metadata-Version: 2.1
Name: mesconduit
Version: 1.1.2
Summary: Python & Conduit Integration Library
Home-page: https://github.com/pypa/sampleproject
Author: Melvin Paul Miki
Author-email: author@example.com
License: UNKNOWN
Project-URL: Bug Tracker, https://github.com/pypa/sampleproject/issues
Platform: UNKNOWN
Classifier: Programming Language :: Python :: 3
Classifier: License :: OSI Approved :: MIT License
Classifier: Operating System :: OS Independent
Requires-Python: >=3.6
Requires-Dist: requests
Requires-Dist: logging
Requires-Dist: json
Requires-Dist: os
